setup.py
bin/img_rotate
img_rotate/__init__.py
img_rotate.egg-info/PKG-INFO
img_rotate.egg-info/SOURCES.txt
img_rotate.egg-info/dependency_links.txt
img_rotate.egg-info/not-zip-safe
img_rotate.egg-info/top_level.txt