Metadata-Version: 1.0
Name: img-rotate
Version: 0.1
Summary: Rotates PIL Image instances after EXIF-tagged image orientation
Home-page: https://github.com/kylefox/python-image-orientation-patch
Author: Kyle Fox
Author-email: kyle.fox@gmail.com
License: MIT
Platform: UNKNOWN
